README.md
setup.cfg
setup.py
reflexec/__init__.py
reflexec/cli.py
reflexec/reflexec.py
reflexec/signal_handler.py
reflexec.egg-info/PKG-INFO
reflexec.egg-info/SOURCES.txt
reflexec.egg-info/dependency_links.txt
reflexec.egg-info/entry_points.txt
reflexec.egg-info/requires.txt
reflexec.egg-info/top_level.txt
reflexec/config/__init__.py
reflexec/config/validator.py
reflexec/config/watch_config.py
reflexec/config/writer.py
reflexec/output/__init__.py
reflexec/output/ansi.py
reflexec/output/helpers.py
reflexec/output/util.py
reflexec/output/plugin/__init__.py
reflexec/output/plugin/base.py
reflexec/output/plugin/chained.py
reflexec/output/plugin/command.py
reflexec/output/plugin/simple.py
reflexec/output/plugin/terminal.py
reflexec/output/plugin/titlebar.py
reflexec/watcher/__init__.py
reflexec/watcher/plugin/__init__.py
reflexec/watcher/plugin/autodetect.py
reflexec/watcher/plugin/base.py
reflexec/watcher/plugin/inotify.py
reflexec/watcher/plugin/scan.py