Metadata-Version: 2.1
Name: reflexec
Version: 0.2.0
Summary: Utility to automate annoying save-and-run routines in terminal environment
Home-page: https://github.com/ookull/reflexec
Author: Ivar Smolin
Author-email: okul@linux.ee
License: MIT
Download-URL: https://github.com/ookull/reflexec/archive/v0.2.0.tar.gz
Keywords: reflexec
Platform: UNKNOWN
Classifier: Development Status :: 4 - Beta
Classifier: Environment :: Console
Classifier: Intended Audience :: Developers
Classifier: License :: OSI Approved :: MIT License
Classifier: Operating System :: POSIX :: Linux
Classifier: Programming Language :: Python :: 3 :: Only
Classifier: Topic :: Terminals
Classifier: Topic :: Utilities
Requires-Python: >=3.5
